wiredseleniumdf/README.MD
wiredseleniumdf/__init__.py
wiredseleniumdf/requirements.txt
wiredseleniumdf/thirdparty.json
wiredseleniumdf-0.10.dist-info/LICENSE.rst
wiredseleniumdf-0.10.dist-info/METADATA
wiredseleniumdf-0.10.dist-info/WHEEL
wiredseleniumdf-0.10.dist-info/top_level.txt
wiredseleniumdf-0.10.dist-info/RECORD
