Metadata-Version: 2.1
Name: wiredseleniumdf
Version: 0.10
Summary: captures and processes network requests (selenium-wire and undetected-chromedriver) and converts them to pandas DataFrames
Home-page: https://github.com/hansalemaos/wiredseleniumdf
Author: Johannes Fischer
Author-email: aulasparticularesdealemaosp@gmail.com
License: MIT
Keywords: requests,POST,GET
Classifier: Development Status :: 4 - Beta
Classifier: Programming Language :: Python :: 3 :: Only
Classifier: Programming Language :: Python :: 3.10
Classifier: Topic :: Software Development :: Libraries :: Python Modules
Classifier: Topic :: Utilities
License-File: LICENSE.rst
Requires-Dist: a-pandas-ex-dillpickle
Requires-Dist: keyboard
Requires-Dist: kthread
Requires-Dist: kthread-sleep
Requires-Dist: multikeyiterdict
Requires-Dist: pandas
Requires-Dist: selenium-wire
